Workbook

Sheet Research Gap
A1: No | B1: Judul Paper | C1: Nama Author | D1: Tahun terbit | E1: Nama Jurnal/Conference | F1: Masalah yang disolusikan | G1: Penjelasan solusi/metode yang diangkat | H1: Kelebihan metode pada paper | I1: Kekurangan metode yang diajukan di paper | J1: Link paper
A2: 1 | B2: A Comprehensive Tutorial and Survey of O-RAN: Exploring Slicing-aware Architecture, Deployment Options, Use Cases, and Challenges | C2: Khurshid Alam; Mohammad Asif Habibi; Matthias Tammen; Dennis Krummacker; Walid Saad; Marco Di Renzo; Tommaso Melodia; Xavier Costa-Pérez; Mérouane Debbah; Ashutosh Dutta; Hans D. Schotten | D2: 2025 | E2: arXiv | F2: Arsitektur O-RAN yang mendukung slicing dari RAN hingga transport/core, deployment, dan orkestrasi. | G2: Tutorial dan survei spesifikasi O-RAN Alliance, 3GPP, ETSI, serta literatur; pemetaan komponen, antarmuka, subnet slice, dan deployment. | H2: Menyatukan perspektif network slicing, management slicing, O-Cloud, RAN dan transport. Interoperabilitas serta koordinasi resource lintas domain dibutuhkan untuk slicing end-to-end. | I2: Pendekatan pada paper ini masih bersifat survei dan konseptual sehingga belum menyediakan implementasi pengendali yang dapat diuji secara langsung. Konflik antar-aplikasi, sinkronisasi sumber daya, orkestrasi lintas domain, monitoring, serta interoperabilitas juga masih menjadi tantangan, terutama untuk menjamin SLA dan stabilitas layanan secara terukur. | J2: https://arxiv.org/abs/2405.03555v5
A3: 2 | B3: Contract-based Agentic Intent Framework for Network Slicing in O-RAN | C3: Fransiscus Asisi Bimo; Chun-Kai Lai; Zhi-Yuan Yang; Ray-Guang Cheng | D3: 2026 | E3: arXiv | F3: Intent bahasa alami yang divalidasi contract sebelum actuation rApp/xApp untuk network slicing. | G3: Profiling agent Qwen3-4B, evaluator Llama Nemotron 49B; TMF921/JSON-LD Intent Contract; A1 policy dan E2 RRM ratio; iterative refinement. | H3: Validasi kontrak meningkatkan keandalan semantic translation; closed-loop mengikuti target throughput di lingkungan RAN simulator. Safety berlaku terhadap aturan contract dan skenario yang diuji. | I3: Dataset dan skenario evaluasi masih terbatas sehingga kemampuan framework untuk menangani berbagai jenis intent belum dapat digeneralisasi. Use case seperti energy saving dan traffic steering belum diuji, sedangkan konflik intent simultan, robustness terhadap input adversarial, dan jaminan safety di luar aturan kontrak yang telah ditentukan masih terbuka. | J3: https://arxiv.org/abs/2603.01663v1
A4: 3 | B4: On Deep Reinforcement Learning for Traffic Steering Intelligent ORAN | C4: Fatemeh Kavehmadavani; Van-Dinh Nguyen; Thang X. Vu; Symeon Chatzinotas | D4: 2023 | E4: arXiv | F4: Traffic steering eMBB/URLLC dengan slicing, multi-connectivity dan mixed numerology. | G4: Hierarki heuristik, DDQN multi-agent untuk RB assignment, serta successive convex approximation untuk variabel kontinu; kendali pada beberapa horizon. | H4: Traffic flow splitting dan numerology adaptif memperbaiki throughput dengan mempertimbangkan latency URLLC pada simulasi. | I4: Pendekatan masih dievaluasi melalui simulasi dan belum dibuktikan melalui deployment xApp pada lingkungan O-RAN nyata. Skalabilitas ketika jumlah UE atau resource meningkat, overhead antarmuka RIC–RAN, serta ketahanan algoritma terhadap keterlambatan atau informasi state yang sudah tidak aktual belum dievaluasi secara menyeluruh. | J4: https://arxiv.org/abs/2311.03853v1
A5: 4 | B5: Exploiting and Securing ML Solutions in Near-RT RIC: A Perspective of an xApp | C5: Thusitha Dayaratne; Viet Vo; Shangqi Lai; Sharif Abuadbba; Blake Haydon; Hajime Suzuki; Xingliang Yuan; Carsten Rudolph | D5: 2024 | E5: arXiv | F5: Attack surface ML traffic-steering xApp pada Near-RT RIC dan pendekatan pertahanan. | G5: Analisis arsitektur dan threat model malicious xApp; telaah SDL/RMR, API dan akses model; kategori adversarial ML serta serangan resource/network. | H5: Satu xApp berbahaya dapat mengakses vektor data/model poisoning, inference/evasion, manipulasi komunikasi dan exhaustion; defense memerlukan autentikasi, isolation, monitoring dan data provenance. | I5: Paper lebih berfokus pada identifikasi attack surface dan threat model dibandingkan implementasi mekanisme pertahanan yang lengkap. Efektivitas autentikasi, isolation, monitoring, dan data provenance belum dibandingkan melalui eksperimen serangan secara menyeluruh, termasuk overhead latency yang dapat muncul ketika mekanisme keamanan diterapkan pada Near-RT RIC. | J5: https://arxiv.org/abs/2406.12299v1
A6: 5 | B6: INA-Infra: An Open and Extensible Infrastructure for Intent-driven Network Automation Research | C6: Nguyen-Bao-Long Tran; Tuan V. Ngo; Mao V. Ngo; Binbin Chen; Jihong Park; Tony Q. S. Quek | D6: 2024 | E6: arXiv | F6: Infrastruktur end-to-end 5G dan intent-driven provisioning resource radio, compute, serta jaringan. | G6: Integrasi komponen open-source O-RAN dan Nephio/Kubernetes; Resource Management rApp dan Network Slicing xApp; intent traffic class diterjemahkan ke deployment/resource. | H6: Intent tingkat tinggi dapat memicu provisioning dan kendali slicing. Pada kapasitas terbatas, prioritas menentukan pembagian throughput namun tidak menghilangkan seluruh pelanggaran SLA. | I6: Infrastruktur mampu menerjemahkan intent menjadi provisioning dan kontrol jaringan, tetapi belum dapat menjamin bahwa seluruh SLA dapat dipenuhi ketika kapasitas sumber daya terbatas. Mekanisme formal untuk admission control, validasi feasibility, kontrak intent, rollback, dan koordinasi sumber daya lintas domain belum menjadi bagian utama evaluasi. | J6: https://arxiv.org/abs/2410.09765v1
A7: 6 | B7: Intelligent O-RAN Traffic Steering for URLLC Through Deep Reinforcement Learning | C7: Ibrahim Tamim; Sam Aleyadeh; Abdallah Shami | D7: 2023 | E7: arXiv | F7: Traffic steering proaktif untuk menghindari kemacetan dan mengurangi queuing delay URLLC. | G7: Dua tier: Naive Bayes untuk prediksi congestion, deep Q-learning untuk memilih service function chain/rerouting; input kondisi VNF. | H7: Antisipasi kemacetan memberi queuing delay lebih kecil dibanding reactive traffic steering pada dataset URLLC simulasi. | I7: Pengujian masih menggunakan traffic URLLC berbasis simulasi dan belum dilakukan pada deployment O-RAN nyata dengan skala trafik yang lebih besar. Penurunan queuing delay belum secara langsung membuktikan terpenuhinya reliability URLLC atau batas latency end-to-end yang sangat ketat, terutama jika prediksi congestion mengalami kesalahan. | J7: https://arxiv.org/abs/2303.01960v1
A8: 7 | B8: Intent-driven Intelligent Control and Orchestration in O-RAN Via Hierarchical Reinforcement Learning | C8: Md Arafat Habib; Hao Zhou; Pedro Enrique Iturria-Rivera; Medhat Elsayed; Majid Bavand; Raimundas Gaigalas; Yigit Ozcan; Melike Erol-Kantarci | D8: 2023 | E8: arXiv | F8: Orkestrasi multiple xApp berdasarkan intent KPI throughput dan efisiensi energi. | G8: HRL dua level: meta-controller memilih target KPI, controller menentukan kombinasi/orchestration xApp; contoh traffic steering dan cell sleeping. | H8: Pemilihan kombinasi xApp berbasis intent meningkatkan KPI dibanding satu xApp atau orchestration non-ML. | I8: Intent yang digunakan masih berupa target KPI yang relatif eksplisit sehingga belum menunjukkan kemampuan memahami intent bahasa alami yang kompleks atau ambigu. Konflik antar-KPI, hard constraint, interaksi antar-xApp, serta waktu yang diperlukan untuk menjalankan keputusan hierarchical reinforcement learning pada deployment nyata juga belum divalidasi secara menyeluruh. | J8: https://arxiv.org/abs/2307.02754v1
A9: 8 | B9: Machine Learning-enabled Traffic Steering in O-RAN: A Case Study on Hierarchical Learning Approach | C9: Md Arafat Habib; Hao Zhou; Pedro Enrique Iturria-Rivera; Yigit Ozcan; Medhat Elsayed; Majid Bavand; Raimundas Gaigalas; Melike Erol-Kantarci | D9: 2025 | E9: IEEE Communications Magazine | F9: Survey ML traffic steering dan case study hierarchical deep Q-learning. | G9: h-DQN: meta-controller policy long-term; controller tindakan TS instant; simulasi dibanding threshold heuristic dan DRL single-layer. | H9: Hierarchical intelligence meningkatkan throughput dan delay pada perubahan traffic load dibanding baseline non-hierarkis. | I9: Peningkatan throughput dan delay masih dibuktikan melalui simulasi, sedangkan evaluasi pada testbed O-RAN nyata belum dilakukan. Metode juga belum memberikan jaminan safety atau tail latency dan belum menunjukkan bagaimana performanya berubah apabila state yang diterima oleh dua tingkat kontrol mengalami delay atau menjadi tidak aktual. | J9: https://doi.org/10.1109/MCOM.002.2300526
A10: 9 | B10: ORANSlice: An Open-Source 5G Network Slicing Platform for O-RAN | C10: Hai Cheng; Salvatore D’Oro; Rajeev Gangula; Sakthivel Velumani; Davide Villa; Leonardo Bonati; Michele Polese; Gabriel Arrobo; Christian Maciocco; Tommaso Melodia | D10: 2024 | E10: arXiv | F10: Platform open-source 5G slicing dengan scheduler programmable dan kontrol xApp. | G10: Ekstensi OAI; slicing mengikuti RRMPolicyMin/Max/DedicatedRatio; service model berbasis E2SM-CCC dan OSC Near-RT RIC; uji dua OTA testbed serta RF simulator. | H10: Slice prioritization, minimum PRB guarantee dan update ratio melalui xApp dapat dijalankan pada OAI; platform menyediakan substrate untuk algoritma lanjutan. | I10: Jaminan minimum resource seperti PRB belum secara otomatis menjamin terpenuhinya latency, reliability, atau SLA aplikasi. Controller yang didemonstrasikan juga belum dilengkapi dengan validasi intent, mekanisme safety, learning adaptif, atau koordinasi kontrol secara lengkap pada beberapa timescale. | J10: https://arxiv.org/abs/2410.12978v1
A11: 10 | B11: Open RAN LSTM Traffic Prediction and Slice Management using Deep Reinforcement Learning | C11: Fatemeh Lotfi; Fatemeh Afghah | D11: 2024 | E11: arXiv | F11: Predictive rApp dan distributed DRL xApp untuk slicing pada traffic dinamis. | G11: LSTM meramalkan load di Non-RT RIC; distributed DRL menggunakan informasi actor lokal dan global critic untuk alokasi slice di Near-RT RIC. | H11: Informasi prediction dan pengalaman DU bersama memperbaiki return dan mengurangi QoS violation dibanding DDRL tanpa prediksi. | I11: Evaluasi dilakukan melalui simulasi sehingga dampak prediction error dan distribution shift pada kondisi jaringan nyata belum diketahui. Overhead koordinasi distributed actor–critic, keterlambatan atau kehilangan policy, dan ketergantungan terhadap kualitas prediksi traffic juga belum diuji sebagai bagian dari batas operasional sistem. | J11: https://arxiv.org/abs/2401.06922v1
A12: 11 | B12: Open RAN xApps Design and Evaluation: Lessons Learnt and Identified Challenges | C12: Marcin Hoffmann; Salim Janji; Adam Samorzewski; Łukasz Kułacz; Cezary Adamczyk; Marcin Dryjański; Paweł Kryszkiewicz; Adrian Kliks; Hanna Bogucka | D12: 2024 | E12: IEEE Journal on Selected Areas in Communications | F12: Desain, implementasi dan evaluasi xApp/rApp serta hambatan platform open-source. | G12: Perbandingan platform dan empat aplikasi terpilih: beam mobility, signaling storm protection, traffic steering, QoS resource allocation; lessons learned berbasis implementasi. | H12: Algoritma harus disesuaikan dengan data/control yang benar-benar tersedia; keterbatasan simulator, service model, platform dan conflict mitigation menghambat portability. | I12: Keterbatasan simulator, ketersediaan service model, perbedaan platform, dan belum matangnya mekanisme conflict mitigation dapat mengurangi portabilitas xApp. Selain itu, belum tersedia benchmark lintas-platform yang konsisten untuk membandingkan aplikasi menggunakan workload, antarmuka, dan mekanisme kontrol yang sama. | J12: https://doi.org/10.1109/JSAC.2023.3336190
A13: 12 | B13: RIC-O: Efficient placement of a disaggregated and distributed RAN Intelligent Controller with dynamic clustering of radio nodes | C13: Gabriel M. Almeida; Gustavo Z. Bruno; Alexandre Huff; Matti Hiltunen; Elias P. Duarte Jr.; Cristiano B. Both; Kleber V. Cardoso | D13: 2023 | E13: arXiv | F13: Placement komponen Near-RT RIC di cloud–edge yang memenuhi latency dan efisiensi biaya. | G13: RIC Orchestrator dengan model optimasi exact dan heuristik; disaggregated components, clustering radio nodes; evaluasi analitik dan deployment/redeployment virtual. | H13: Placement menentukan kelayakan loop latency-sensitive; reconfiguration dapat merespons link delay dan node failure, dengan trade-off optimalitas–runtime. | I13: Optimasi placement masih bergantung pada informasi kondisi jaringan yang tersedia dan belum menggunakan prediksi time-series untuk mengantisipasi perubahan sebelum terjadi. Proses redeployment juga dapat menimbulkan downtime, sementara hubungan antara penempatan RIC, SLA slice, dan kualitas tindakan kontrol belum dievaluasi secara terpadu. | J13: https://arxiv.org/abs/2301.02760v1
... A45: 44 | B45: Closed-Loop L4S-as-a-Service in 5G-Advanced: NEF–PCF Control with NWDAF-Driven Assurance | C45: Ameer Shohail L; Ashish Goswami | D45: 2026 | E45: arXiv (preprint; arsitektur dan analisis kontrol) | F45: Closed-loop assurance layanan low-latency dengan menghubungkan intent aplikasi, kebijakan core, dan verifikasi compliance berbasis NWDAF. | G45: AF/NEF intent diterjemahkan PCF menjadi PCC rules melalui SMF/UPF; NWDAF menghitung p99 delay, loss, ECN marking, dan throughput; bounded admission limit, hysteresis, persistence, serta model kontrol discrete-time. | H45: Menghasilkan workflow assurance, kondisi stabilitas lokal, dan batas signaling overhead untuk pemilihan gain serta interval analytics. Kontribusi berupa arsitektur dan formulasi analitis; belum melaporkan performance gain eksperimen. | I45: Paper merupakan preprint yang berfokus pada arsitektur dan model kontrol, sehingga efektivitas pada traffic dan kapasitas berubah belum divalidasi secara empiris. Target p99 delay, loss, dan analytics window merupakan konfigurasi usulan, bukan hasil yang telah dicapai. Aksi utama adalah admission/policy control di core; diagnosis lokasi bottleneck, implementasi RIC–NWDAF, dan pemulihan SLA multi-slice belum dievaluasi. | J45: https://arxiv.org/abs/2606.20579

Sheet PAPER
A1: No | B1: Judul Paper | C1: Author | D1: Tahun | E1: DOI / URL
A2: 1 | B2: A Comprehensive Tutorial and Survey of O-RAN: Exploring Slicing-aware Architecture, Deployment Options, Use Cases, and Challenges | C2: Khurshid Alam; Mohammad Asif Habibi; Matthias Tammen; Dennis Krummacker; Walid Saad; Marco Di Renzo; Tommaso Melodia; Xavier Costa-Pérez; Mérouane Debbah; Ashutosh Dutta; Hans D. Schotten | D2: 2025 | E2: https://arxiv.org/abs/2405.03555v5
A3: 2 | B3: A Machine Learning-Driven NWDAF Architecture For Intelligent 5G Core Networks | C3: Tsung-Fang Chen; Chien Chen; Jyh-Cheng Chen | D3: 2025 | E3: https://doi.org/10.1145/3733814.3765498
A4: 3 | B4: Artificial Intelligence for 5G and 6G Networks: A Taxonomy-Based Survey of Applications, Trends, and Challenges | C4: Nouri Omheni; Hend Koubaa; Faouzi Zarai | D4: 2025 | E4: https://doi.org/10.3390/technologies13120559
A5: 4 | B5: Bringing dApps to OCUDU: An E3 Controller for Real-Time Open RAN Intelligence | C5: Angelo Feraudo; Ravis Shirkhani; Stefano Maxenti; Andrea Lacava; Michele Polese; Tommaso Melodia | D5: 2026 | E5: https://doi.org/10.1145/3831662.3844165
A6: 5 | B6: ColO-RAN: Developing Machine Learning-based xApps for Open RAN Closed-loop Control on Programmable Experimental Platforms | C6: Michele Polese; Leonardo Bonati; Salvatore D’Oro; Stefano Basagni; Tommaso Melodia | D6: 2023 | E6: https://doi.org/10.1109/TMC.2022.3188013
A7: 6 | B7: CollabORAN: A Collaborative rApp–xApp–dApp Control Architecture for Fairness-Adaptive Resource Sharing in O-RAN | C7: Anastasios E. Giannopoulos; Sotirios T. Spantideas; Panagiotis Trakadas | D7: 2026 | E7: https://arxiv.org/abs/2603.20805v1
A8: 7 | B8: Contract-based Agentic Intent Framework for Network Slicing in O-RAN | C8: Fransiscus Asisi Bimo; Chun-Kai Lai; Zhi-Yuan Yang; Ray-Guang Cheng | D8: 2026 | E8: https://arxiv.org/abs/2603.01663v1
A9: 8 | B9: DRL-based Latency-Aware Network Slicing in O-RAN with Time-Varying SLAs | C9: Raoul Raftopoulos; Salvatore D’Oro; Tommaso Melodia; Giovanni Schembra | D9: 2024 | E9: https://arxiv.org/abs/2401.05042v3
A10: 9 | B10: On Deep Reinforcement Learning for Traffic Steering Intelligent ORAN | C10: Fatemeh Kavehmadavani; Van-Dinh Nguyen; Thang X. Vu; Symeon Chatzinotas | D10: 2023 | E10: https://arxiv.org/abs/2311.03853v1
A11: 10 | B11: Empowering Traffic Steering in 6G Open RAN With Deep Reinforcement Learning | C11: Fatemeh Kavehmadavani; Van-Dinh Nguyen; Thang X. Vu; Symeon Chatzinotas | D11: 2024 | E11: https://doi.org/10.1109/TWC.2024.3396273
A12: 11 | B12: Exploiting and Securing ML Solutions in Near-RT RIC: A Perspective of an xApp | C12: Thusitha Dayaratne; Viet Vo; Shangqi Lai; Sharif Abuadbba; Blake Haydon; Hajime Suzuki; Xingliang Yuan; Carsten Rudolph | D12: 2024 | E12: https://arxiv.org/abs/2406.12299v1
A13: 12 | B13: INA-Infra: An Open and Extensible Infrastructure for Intent-driven Network Automation Research | C13: Nguyen-Bao-Long Tran; Tuan V. Ngo; Mao V. Ngo; Binbin Chen; Jihong Park; Tony Q. S. Quek | D13: 2024 | E13: https://arxiv.org/abs/2410.09765v1
... A45: 44 | B45: Closed-Loop L4S-as-a-Service in 5G-Advanced: NEF–PCF Control with NWDAF-Driven Assurance | C45: Ameer Shohail L; Ashish Goswami | D45: 2026 | E45: https://arxiv.org/abs/2606.20579

Sheet Analisis Gap
A1: No Paper | B1: Fokus Studi | C1: Metode | D1: Temuan Utama | E1: Keterbatasan / Celah (Gap) | F1: Jenis Gap | G1: Peluang Penelitian | H1: Basis Gap | I1: Lingkungan Evaluasi | J1: Metrik Uji Lanjutan | K1: Judul Paper (Otomatis)
A2: 1 | B2: Arsitektur O-RAN yang mendukung slicing dari RAN hingga transport/core, deployment, dan orkestrasi. | C2: Tutorial dan survei spesifikasi O-RAN Alliance, 3GPP, ETSI, serta literatur; pemetaan komponen, antarmuka, subnet slice, dan deployment. | D2: Menyatukan perspektif network slicing, management slicing, O-Cloud, RAN dan transport. Interoperabilitas serta koordinasi resource lintas domain dibutuhkan untuk slicing end-to-end. | E2: [Penulis] Konflik aplikasi, sinkronisasi resource, orkestrasi multi-domain, monitoring, dan interoperabilitas tetap menjadi tantangan. [Analisis] Survey belum memberikan implementasi pengendali dengan jaminan SLA/stabilitas terukur. | F2: Arsitektur; integrasi; validasi | G2: Rancang koordinasi slicing RAN–transport/core dengan batas resource dan SLA eksplisit; mulai dari model dua domain dan bandingkan dengan optimasi per-domain. | H2: Eksplisit + analisis ruang lingkup | I2: Survei/tutorial; tidak ada eksperimen algoritma baru. | J2: SLA violation rate, latency p95/p99, utilitas resource, waktu orkestrasi, konflik kebijakan. | K2: =INDEX(PAPER!$B$2:$B$45,MATCH(A2,PAPER!$A$2:$A$45,0)) -> A Comprehensive Tutorial and Survey of O-RAN: Exploring Slicing-aware Architecture, Deployment Options, Use Cases, and Challenges
A3: 2 | B3: NWDAF berbasis ML untuk prediksi beban NF dan konfigurasi dinamis charging di 5G Core. | C3: Integrasi NWDAF pada free5GC; MTLF terpisah; LSTM khusus UPF/SMF/CHF; fitur CPU, memori dan metrik operasional; prediksi memicu penyesuaian URR threshold. | D3: Model khusus per NF dan fitur tambahan memperbaiki prediksi. Kontrol URR threshold menghindari saturasi CHF dan pertumbuhan memori SMF yang terjadi pada konfigurasi statis. | E3: [Penulis] Perlu analytics mobilitas UE, online learning, dan kebijakan per-service. [Analisis] Evaluasi berfokus pada charging/core; belum menguji koordinasi RIC–NWDAF untuk SLA RAN–core bersama. | F3: Integrasi lintas domain; adaptasi; cakupan use case | G3: Gabungkan prediksi beban NWDAF dengan keputusan xApp slicing agar resource radio tidak dinaikkan ketika bottleneck berada di core. | H3: Eksplisit + analisis ruang lingkup | I3: free5GC dan UE-Testbed dengan profil trafik realistis; perbandingan konfigurasi statis/dinamis. | J3: SLA E2E, beban CHF/SMF, memory growth, MSE prediksi, throughput, overhead koordinasi. | K3: =INDEX(PAPER!$B$2:$B$45,MATCH(A3,PAPER!$A$2:$A$45,0)) -> A Machine Learning-Driven NWDAF Architecture For Intelligent 5G Core Networks
A4: 3 | B4: Taksonomi AI untuk optimasi, keamanan, predictive analytics, dan lifecycle jaringan 5G/6G. | C4: Survei dengan klasifikasi menurut teknologi, fungsi, domain aplikasi, model terpusat/terdistribusi, serta fase lifecycle. | D4: Arah literatur bergerak menuju intelligence terdistribusi, pengelolaan prediktif, federated learning, edge AI, dan explainable AI; trade-off privasi, akurasi, energi dan latency saling terkait. | E4: [Penulis] Generalisasi, data privacy, scalability, adaptasi dan interoperabilitas membatasi AI jaringan. [Analisis] Taksonomi tidak menyediakan eksperimen O-RAN terkontrol yang mengukur trade-off tersebut secara bersamaan. | F4: Generalisasi; data; evaluasi | G4: Uji model slicing pada traffic shift dan telemetry terbatas; ukur manfaat QoS terhadap biaya komunikasi dan komputasi. | H4: Eksplisit + analisis ruang lingkup | I4: Survei literatur; angka studi rujukan bukan hasil eksperimen baru penulis. | J4: QoS violation, inference latency, energi/CPU, overhead data, generalisasi ke distribusi berbeda. | K4: =INDEX(PAPER!$B$2:$B$45,MATCH(A4,PAPER!$A$2:$A$45,0)) -> Artificial Intelligence for 5G and 6G Networks: A Taxonomy-Based Survey of Applications, Trends, and Challenges
A5: 4 | B5: Portabilitas E3/dApp ke OCUDU untuk akses telemetry PHY dan fronthaul real-time. | C5: E3Controller sebagai sidecar; hook jbpf, shared memory dan libE3; service model Spectrum dan L1; sensing dApp dengan Foxconn RU; ASN.1 dibanding JSON. | D5: Akses I/Q melalui jalur E3 pada OCUDU layak dengan latency sub-ms dan tanpa penalti throughput terukur pada konfigurasi uji. | E5: [Penulis] Ekstensi aktif/injeksi logic untuk scheduling dan PHY masih merupakan future work. [Analisis] Telemetry cepat belum membuktikan closed-loop actuation, deadline saat contention, atau isolation beberapa dApp. | F5: Implementasi/actuation; validasi; skalabilitas | G5: Tambahkan control path dan safety gate untuk tindakan dApp; ukur seluruh loop telemetry–inference–actuation pada kondisi CPU contention. | H5: Eksplisit + analisis ruang lingkup | I5: Eksperimen OCUDU, Foxconn RPQN 4800 RU dan reference sensing dApp; jalur telemetry L1. | J5: Latency loop p99, deadline miss, throughput, overhead CPU/energi, isolation antar-dApp. | K5: =INDEX(PAPER!$B$2:$B$45,MATCH(A5,PAPER!$A$2:$A$45,0)) -> Bringing dApps to OCUDU: An E3 Controller for Real-Time Open RAN Intelligence
A6: 5 | B6: Pipeline pengembangan, training, deployment dan pengujian ML xApp dengan SDR-in-the-loop. | C6: Colosseum/SCOPE dan RIC; autoencoder untuk kompresi KPM; PPO actor–critic untuk slicing/scheduling; training offline dan online; porting ke Arena. | D6: Menyediakan pipeline eksperimen dengan 7 base station, 42 UE dan dataset 3,4 GB. Training online beradaptasi tetapi eksplorasi pada jaringan hidup membawa trade-off kinerja dan waktu. | E6: [Penulis] Training online memiliki trade-off terhadap operasi jaringan dan waktu pelatihan. [Analisis] Portability ke Arena belum menjadi bukti generalisasi seluruh kondisi; safety eksplorasi dan gangguan antar-xApp belum diuji sebagai jaminan. | F6: Sim-to-real/transfer; safety pembelajaran; reproduksibilitas | G6: Tambahkan action shield atau fallback saat online learning; bandingkan PPO asli dan PPO ber-guardrail pada traffic shift. | H6: Eksplisit + analisis ruang lingkup | I6: Colosseum emulator dengan SDR; 7 BS/42 UE; Arena untuk portability. | J6: QoS saat eksplorasi, sample efficiency, waktu recovery, regret, overhead inferensi, transfer performance. | K6: =INDEX(PAPER!$B$2:$B$45,MATCH(A6,PAPER!$A$2:$A$45,0)) -> ColO-RAN: Developing Machine Learning-based xApps for Open RAN Closed-loop Control on Programmable Experimental Platforms
A7: 6 | B7: Koordinasi rApp–xApp–dApp untuk spectrum sharing yang adil pada beberapa timescale. | C7: FrerApp: prediksi traffic LSTM/policy; FrexApp: hypergraph dan PRB coloring; FredApp: temporal PRB sharing/fairness. Loop menit, detik, milidetik. | D7: Hierarki tiga lapis menyeimbangkan satisfaction rate dan fairness lebih baik dibanding rApp–xApp saja atau xApp–dApp saja. | E7: [Analisis] Bukti berupa simulasi spectrum allocation; latency komunikasi, telemetry stale, deployment dApp dan stabilitas saat ketiga loop terlambat belum dibuktikan. Integrasi contract intent juga belum menjadi fokus. | F7: Validasi real-system; koordinasi temporal; safety | G7: Uji koordinasi tiga loop dengan delay/drop telemetry; tambahkan policy versioning, hysteresis dan batas tindakan untuk mencegah konflik. | H7: Analisis ruang lingkup/evaluasi | I7: Simulasi macro/micro RU, traffic harian dan variasi demand; rApp interval 15 menit. | J7: Jain fairness, satisfaction rate, starvation, perubahan PRB, oscillation, deadline miss. | K7: =INDEX(PAPER!$B$2:$B$45,MATCH(A7,PAPER!$A$2:$A$45,0)) -> CollabORAN: A Collaborative rApp–xApp–dApp Control Architecture for Fairness-Adaptive Resource Sharing in O-RAN
A8: 7 | B8: Intent bahasa alami yang divalidasi contract sebelum actuation rApp/xApp untuk network slicing. | C8: Profiling agent Qwen3-4B, evaluator Llama Nemotron 49B; TMF921/JSON-LD Intent Contract; A1 policy dan E2 RRM ratio; iterative refinement. | D8: Validasi kontrak meningkatkan keandalan semantic translation; closed-loop mengikuti target throughput di lingkungan RAN simulator. Safety berlaku terhadap aturan contract dan skenario yang diuji. | E8: [Penulis] Dataset perlu diperluas; use case energy saving/traffic steering belum dievaluasi. [Analisis] Belum membuktikan safety universal, lifecycle konflik simultan atau robustness adversarial; baseline dan CAIF memakai komposisi model berbeda. | F8: Safety/verification; validitas evaluasi; generalisasi | G8: Uji contract dengan intent konflik, telemetry stale dan SLA berubah; lakukan ablation menggunakan model dasar yang sama untuk mengisolasi manfaat contract. | H8: Eksplisit + analisis kontrol eksperimen | I8: 500 intent; VIAVI AI RSG v2.6, 3 gNB/120 UE dan dua slice. RAN disimulasikan, bukan OTA smartphone. | J8: Unsafe actuation, semantic accuracy, false rejection, latency p95, recovery, SLA violation. | K8: =INDEX(PAPER!$B$2:$B$45,MATCH(A8,PAPER!$A$2:$A$45,0)) -> Contract-based Agentic Intent Framework for Network Slicing in O-RAN
A9: 8 | B9: Slicing yang menyesuaikan alokasi PRB saat target latency SLA berubah tanpa retraining. | C9: State/reward DRL memasukkan SLA yang berubah; PPO; data OpenRAN Gym/Colosseum; baseline DQN dan Q-learning. | D9: PPO yang mengetahui SLA mengurangi pelanggaran dibanding baseline dan beradaptasi pada target latency yang bervariasi. | E9: [Penulis] Multi-agent untuk SLA berbeda dan target KPM beragam masih future work. [Analisis] Skenario DYN menggunakan satu slice dan rentang SLA 10–110 ms; tidak membuktikan hard guarantee untuk banyak slice yang berebut resource. | F9: Multi-objective/multi-slice; generalisasi SLA; safety | G9: Perluas ke multi-slice dengan SLA berubah bersamaan dan admission control; bandingkan PPO SLA-aware dengan constrained PPO/shield. | H9: Eksplisit + analisis ruang lingkup | I9: Training/evaluasi dengan data OpenRAN Gym/Colosseum; STAT dan DYN; dua konfigurasi evaluasi DYN karena keterbatasan ruang. | J9: Violation rate per-slice, latency p99, PRB usage, waktu adaptasi, fairness dan admission rejection. | K9: =INDEX(PAPER!$B$2:$B$45,MATCH(A9,PAPER!$A$2:$A$45,0)) -> DRL-based Latency-Aware Network Slicing in O-RAN with Time-Varying SLAs
A10: 9 | B10: Traffic steering eMBB/URLLC dengan slicing, multi-connectivity dan mixed numerology. | C10: Hierarki heuristik, DDQN multi-agent untuk RB assignment, serta successive convex approximation untuk variabel kontinu; kendali pada beberapa horizon. | D10: Traffic flow splitting dan numerology adaptif memperbaiki throughput dengan mempertimbangkan latency URLLC pada simulasi. | E10: [Penulis] Scalability/adaptability sesuai spesifikasi O-RAN dan 3GPP perlu diteliti lanjut. [Analisis] Belum ada pembuktian deployment xApp, overhead antarmuka dan ketahanan terhadap delay state. | F10: Implementasi; scalability; validasi timing | G10: Implementasikan versi ringan untuk Near-RT; evaluasi penurunan manfaat saat channel/telemetry terlambat dan biaya optimasi meningkat. | H10: Eksplisit + analisis ruang lingkup | I10: Simulasi system-level downlink multi-service; perbandingan upper bound, fixed numerology dan uniform flow split. | J10: Throughput eMBB, latency URLLC, queue length, runtime optimasi, overhead telemetry. | K10: =INDEX(PAPER!$B$2:$B$45,MATCH(A10,PAPER!$A$2:$A$45,0)) -> On Deep Reinforcement Learning for Traffic Steering Intelligent ORAN
A11: 10 | B11: Traffic steering slice-aware pada multiple timescale dan traffic/channel yang berubah. | C11: LSTM untuk prediksi trafik; heuristik/flow-splitting; multi-agent double DQN untuk scheduling RB; optimasi short-term di DU, kebijakan melalui RIC. | D11: Menggabungkan prediksi dan scheduling adaptif memberi throughput eMBB lebih tinggi dibanding slice isolation sambil memenuhi kendala URLLC dalam model. | E11: [Penulis] Framework mengasumsikan latency pertukaran keputusan/policy RIC–RAN dapat diabaikan. [Analisis] Efek delay, loss, stale prediction dan interaksi aplikasi pada deployment nyata belum tervalidasi. | F11: Asumsi temporal; implementasi; robustness | G11: Rancang delay-aware policy dan confidence-aware forecast; injeksikan delay/loss A1/E2 untuk mengukur kapan prediksi perlu diabaikan. | H11: Eksplisit + analisis ruang lingkup | I11: Simulasi; variasi daya, traffic load, channel dan baseline slice isolation/fixed numerology/uniform split. | J11: Throughput, worst URLLC latency, backlog, runtime, SLA violations terhadap delay telemetri. | K11: =INDEX(PAPER!$B$2:$B$45,MATCH(A11,PAPER!$A$2:$A$45,0)) -> Empowering Traffic Steering in 6G Open RAN With Deep Reinforcement Learning
A12: 11 | B12: Attack surface ML traffic-steering xApp pada Near-RT RIC dan pendekatan pertahanan. | C12: Analisis arsitektur dan threat model malicious xApp; telaah SDL/RMR, API dan akses model; kategori adversarial ML serta serangan resource/network. | D12: Satu xApp berbahaya dapat mengakses vektor data/model poisoning, inference/evasion, manipulasi komunikasi dan exhaustion; defense memerlukan autentikasi, isolation, monitoring dan data provenance. | E12: [Penulis] Defense, provenance dan hardware-assisted isolation perlu dikembangkan tanpa mengganggu real-time. [Analisis] Paper terutama analisis ancaman; tidak memberikan benchmark eksperimen attack/defense dan latency overhead. | F12: Security; validasi empiris; trade-off latency | G12: Bangun threat-injection pada telemetry/KPM xApp; evaluasi lightweight anomaly detection dan action validation terhadap manfaat QoS serta overhead. | H12: Eksplisit + analisis jenis bukti | I12: Analisis keamanan use case traffic steering; bukan kampanye eksperimen dengan attack success rate terukur. | J12: Attack success, unsafe actions, false positives, SLA degradation, detection delay, CPU/latency overhead. | K12: =INDEX(PAPER!$B$2:$B$45,MATCH(A12,PAPER!$A$2:$A$45,0)) -> Exploiting and Securing ML Solutions in Near-RT RIC: A Perspective of an xApp
A13: 12 | B13: Infrastruktur end-to-end 5G dan intent-driven provisioning resource radio, compute, serta jaringan. | C13: Integrasi komponen open-source O-RAN dan Nephio/Kubernetes; Resource Management rApp dan Network Slicing xApp; intent traffic class diterjemahkan ke deployment/resource. | D13: Intent tingkat tinggi dapat memicu provisioning dan kendali slicing. Pada kapasitas terbatas, prioritas menentukan pembagian throughput namun tidak menghilangkan seluruh pelanggaran SLA. | E13: [Analisis] Infrastruktur automation belum menjamin semua SLA feasible; hasil menunjukkan violation pada slice yang bersaing. Formal contract, admission control dan rollback lintas domain belum menjadi evaluasi inti. | F13: Assurance/SLA; feasibility; integrasi | G13: Tambahkan feasibility checking sebelum menerima intent serta assurance setelah deployment; alokasi ulang harus mempertimbangkan bottleneck radio/compute. | H13: Analisis hasil dan ruang lingkup | I13: Infrastruktur 5G/O-RAN end-to-end berbasis open-source; eksperimen dengan traffic class dan prioritas slice. | J13: SLA violation per-slice, provisioning latency, rejection yang benar, resource efficiency, recovery. | K13: =INDEX(PAPER!$B$2:$B$45,MATCH(A13,PAPER!$A$2:$A$45,0)) -> INA-Infra: An Open and Extensible Infrastructure for Intent-driven Network Automation Research
... A45: 44 | B45: Closed-loop assurance layanan low-latency dengan menghubungkan intent aplikasi, kebijakan core, dan verifikasi compliance berbasis NWDAF. | C45: AF/NEF intent diterjemahkan PCF menjadi PCC rules melalui SMF/UPF; NWDAF menghitung p99 delay, loss, ECN marking, dan throughput; bounded admission limit, hysteresis, persistence, serta model kontrol discrete-time. | D45: Menghasilkan workflow assurance, kondisi stabilitas lokal, dan batas signaling overhead untuk pemilihan gain serta interval analytics. Kontribusi berupa arsitektur dan formulasi analitis; belum melaporkan performance gain eksperimen. | E45: [Penulis] Deployment-specific validation, traffic mix, kapasitas berubah, dan trade-off admission/secondary action/analytics cadence merupakan future work. [Analisis] Core-driven assurance belum mengevaluasi diagnosis RAN/core dan pemilihan domain traffic-steering melalui koordinasi RIC–NWDAF. | F45: Validasi empiris; integrasi lintas domain; cakupan aksi | G45: Implementasikan feedback NWDAF dan core adapter bersama rApp/xApp; gunakan diagnosis untuk memilih steering dibanding admission/policy saja, lalu ukur stabilitas dan QoS recovery pada slice dengan kebutuhan berbeda. | H45: Eksplisit + analisis ruang lingkup | I45: Preprint arsitektur dan model analitis; blueprint evaluasi dengan baseline no assurance, L4S tanpa adaptasi, dan NWDAF-driven adaptation. Belum ada hasil simulasi/testbed kinerja. | J45: P99 delay, packet loss ratio, CE-marking ratio, throughput, convergence/QoS recovery time, policy update rate, signaling overhead, SLA violation per slice. | K45: =INDEX(PAPER!$B$2:$B$45,MATCH(A45,PAPER!$A$2:$A$45,0)) -> Closed-Loop L4S-as-a-Service in 5G-Advanced: NEF–PCF Control with NWDAF-Driven Assurance

Sheet SOTA
A1: No Paper | B1: Aspek | C1: Kondisi Terkini (SOTA) | D1: Pencapaian / Benchmark | E1: Keterbatasan SOTA Saat Ini | F1: Posisi Penelitian Anda (Usulan) | G1: Judul Paper (Otomatis)
A2: 1 | B2: Fondasi slicing-aware O-RAN | C2: Arsitektur dan opsi deployment slicing dapat dipetakan pada antarmuka/manajemen O-RAN; integrasi end-to-end masih menjadi pekerjaan sistem. | D2: Kontribusi berupa pemetaan standar, use case, dan tantangan; tidak menyediakan benchmark kinerja eksperimen baru. | E2: Deskripsi arsitektur tidak membuktikan end-to-end SLA atau interoperabilitas implementasi. | F2: Usulan: gunakan sebagai fondasi arsitektur; kontribusi berada pada implementasi koordinasi dan evaluasi SLA lintas domain. | G2: =INDEX(PAPER!$B$2:$B$45,MATCH(A2,PAPER!$A$2:$A$45,0)) -> A Comprehensive Tutorial and Survey of O-RAN: Exploring Slicing-aware Architecture, Deployment Options, Use Cases, and Challenges
A3: 2 | B3: Closed-loop intelligence di 5G Core | C3: NWDAF open-source sudah dapat memprediksi beban NF dan memicu actuation konfigurasi core. | D3: Tabel 2: MSE CHF turun 35,31 menjadi 19,61 dengan fitur SMF tambahan; baseline statis mencapai CPU CHF 100%, sistem dinamis menghindari saturasi pada skenario uji. | E3: Hasil charging tidak otomatis berlaku untuk latency/throughput slice end-to-end atau domain RAN. | F3: Usulan: perluas dari core-only ke RAN–core coordination; bandingkan uncoordinated controller dengan joint bottleneck-aware controller. | G3: =INDEX(PAPER!$B$2:$B$45,MATCH(A3,PAPER!$A$2:$A$45,0)) -> A Machine Learning-Driven NWDAF Architecture For Intelligent 5G Core Networks
A4: 3 | B4: Taksonomi dan trustworthy AI jaringan | C4: AI sudah mencakup lifecycle jaringan dan berbagai domain; FL, edge AI dan XAI menjadi pendekatan yang banyak dibahas. | D4: Tidak ada benchmark baru yang sebanding langsung; tabel merangkum manfaat dan keterbatasan penelitian lain. | E4: Cakupan luas; tidak membuktikan readiness satu pipeline O-RAN atau keunggulan algoritma tertentu. | F4: Usulan: gunakan untuk kategorisasi kontribusi dan metrik trade-off; klaim novelty harus ditopang paper teknis spesifik. | G4: =INDEX(PAPER!$B$2:$B$45,MATCH(A4,PAPER!$A$2:$A$45,0)) -> Artificial Intelligence for 5G and 6G Networks: A Taxonomy-Based Survey of Applications, Trends, and Challenges
A5: 4 | B5: Implementasi E3 lintas platform | C5: E3 sudah diperluas ke OCUDU dengan instrumentasi ringan dan controller di luar pemrosesan inti RAN. | D5: Median latency jalur L1 sekitar 115–120 µs, IQR sekitar 10 µs; tidak ada penalti throughput terukur. Ini benchmark telemetry, bukan loop kontrol penuh. | E5: Actuation dinamis dan ekstensi programmable RAN masih arah lanjutan; angka bergantung konfigurasi testbed. | F5: Usulan: ukur dan amankan closed-loop actuation lintas platform; gunakan latency telemetry sebagai komponen anggaran, bukan target loop lengkap. | G5: =INDEX(PAPER!$B$2:$B$45,MATCH(A5,PAPER!$A$2:$A$45,0)) -> Bringing dApps to OCUDU: An E3 Controller for Real-Time Open RAN Intelligence
A6: 5 | B6: Eksperimen ML xApp yang dapat direproduksi | C6: Training–testing–deployment closed-loop dapat disatukan pada platform RAN programmable dan dipindahkan ke testbed lain. | D6: 7 BS, 42 UE, dataset 3,4 GB; online training Colosseum memerlukan sekitar 30% lebih sedikit langkah daripada offline, tetapi waktu nyata lebih lama. | E6: Skala eksperimen dan portability tertentu tidak menjamin safety/generalization pada jaringan produksi. | F6: Usulan: jadikan pipeline/baseline PPO; tambah perlindungan eksplorasi dan pengujian transfer pada gangguan yang terukur. | G6: =INDEX(PAPER!$B$2:$B$45,MATCH(A6,PAPER!$A$2:$A$45,0)) -> ColO-RAN: Developing Machine Learning-based xApps for Open RAN Closed-loop Control on Programmable Experimental Platforms
A7: 6 | B7: Koordinasi tiga timescale | C7: Collaborative rApp–xApp–dApp sudah memiliki desain fungsional dan pembanding ablation dua lapis. | D7: Simulasi demand 1–3 Mbps: CollabORAN success rate >91% dan JFI >92%; dua lapis menunjukkan trade-off satisfaction–fairness. | E7: Keunggulan simulasi belum memastikan real-time feasibility atau stabilitas saat antarmuka/telemetry terganggu. | F7: Usulan: perluas evaluasi dari koordinasi ideal ke delay-aware coordination dan perlindungan tindakan; bukan sekadar menambah lapisan dApp. | G7: =INDEX(PAPER!$B$2:$B$45,MATCH(A7,PAPER!$A$2:$A$45,0)) -> CollabORAN: A Collaborative rApp–xApp–dApp Control Architecture for Fairness-Adaptive Resource Sharing in O-RAN
A8: 7 | B8: Guardrail untuk agentic intent | C8: Intent extraction dapat dipisahkan dari policy execution melalui contract dan evaluator; validasi format saja belum cukup. | D8: CAIF 499/500 (99,8%) vs baseline 96,8%; CI95% CAIF 98,9–100%. Latency 1-shot 11,8 s vs 8,5 s baseline; actuation melalui loop xApp terpisah. | E8: Dataset kurasi dan RAN simulasi; latency detik tidak cocok untuk inference Near-RT langsung; perbedaan model adalah faktor pembanding. | F8: Usulan: kontrak yang diperbarui berdasarkan state/SLA dan diuji pada intent konflik; ukur safety sekaligus false rejection dan overhead. | G8: =INDEX(PAPER!$B$2:$B$45,MATCH(A8,PAPER!$A$2:$A$45,0)) -> Contract-based Agentic Intent Framework for Network Slicing in O-RAN
A9: 8 | B9: DRL yang beradaptasi terhadap SLA | C9: SLA dapat menjadi input policy DRL sehingga perubahan target tidak selalu memerlukan retraining. | D9: Violation rate 8,3× lebih rendah dari DQN dan 14,4× dari Q-learning. Penulis melaporkan pemakaian PRB lebih rendah; frasa 0,3×/0,6× less tidak dikonversi menjadi persen karena ambigu. | E9: Pelanggaran tetap probabilistik; rentang SLA dan jumlah slice uji terbatas. | F9: Usulan: kemampuan SLA-aware dijadikan baseline, lalu tambah batas aman dan koordinasi multi-slice di bawah resource scarcity. | G9: =INDEX(PAPER!$B$2:$B$45,MATCH(A9,PAPER!$A$2:$A$45,0)) -> DRL-based Latency-Aware Network Slicing in O-RAN with Time-Varying SLAs
A10: 9 | B10: Hybrid DRL–optimization traffic steering | C10: Steering dapat digabung dengan alokasi RB, flow split dan numerology; algoritma hybrid melampaui baseline sederhana. | D10: Throughput +45,50% vs fixed numerology dan +10,26% vs Uniform-φ pada Pmax=30 dBm dalam simulasi. | E10: Keunggulan berlaku pada baseline/parameter tersebut; belum menjadi benchmark xApp operasional. | F10: Usulan: ukur robustness timing dan runtime; gunakan sebagai baseline hybrid, hindari klaim baru hanya karena memakai DRL. | G10: =INDEX(PAPER!$B$2:$B$45,MATCH(A10,PAPER!$A$2:$A$45,0)) -> On Deep Reinforcement Learning for Traffic Steering Intelligent ORAN
A11: 10 | B11: Predictive multi-timescale traffic steering | C11: Traffic forecasting dan multi-agent DRL sudah digabungkan dengan kontrol lintas timescale. | D11: Pada Pmax=30 dBm: throughput +99,42% vs time-domain slice isolation; +43,39% vs frequency-domain isolation; +40,74% vs fixed numerology (Fig.8). | E11: Negligible communication latency adalah asumsi eksplisit; angka throughput tidak sebanding langsung dengan benchmark regret/fairness. | F11: Usulan: kontribusi pada toleransi delay dan stale prediction, disertai ablation prediksi/koordinasi. | G11: =INDEX(PAPER!$B$2:$B$45,MATCH(A11,PAPER!$A$2:$A$45,0)) -> Empowering Traffic Steering in 6G Open RAN With Deep Reinforcement Learning
A12: 11 | B12: Keamanan ML xApp | C12: Threat model pada komponen RIC dan model ML telah dipetakan; mitigasi harus menyentuh akses, komunikasi dan input keputusan. | D12: Tidak melaporkan benchmark attack/defense numerik baru; kontribusi utama pemetaan ancaman dan mekanisme pertahanan. | E12: Efektivitas pertahanan dan kelayakan Near-RT belum dibuktikan secara empiris dalam paper ini. | F12: Usulan: validasi keamanan operasional dengan serangan terkontrol dan metrik QoS/timing, bukan hanya enumerasi ancaman. | G12: =INDEX(PAPER!$B$2:$B$45,MATCH(A12,PAPER!$A$2:$A$45,0)) -> Exploiting and Securing ML Solutions in Near-RT RIC: A Perspective of an xApp
A13: 12 | B13: Intent-driven infrastructure automation | C13: Provisioning infrastruktur dan kontrol slicing dapat dihubungkan dalam satu platform penelitian open-source. | D13: Skenario S3/S4/S5: throughput rata-rata 15/25/65 Mbps dan violation 50%/45%/28%; slice prioritas tinggi tetap mengalami violation saat kompetisi. | E13: Automation berhasil tidak sama dengan jaminan SLA; kapasitas dan konflik intent menentukan hasil. | F13: Usulan: perluas platform dengan admission/feasibility check dan assurance dinamis untuk intent yang bersaing. | G13: =INDEX(PAPER!$B$2:$B$45,MATCH(A13,PAPER!$A$2:$A$45,0)) -> INA-Infra: An Open and Extensible Infrastructure for Intent-driven Network Automation Research
... A45: 44 | B45: NWDAF-driven closed-loop latency assurance di core | C45: NEF–PCF–SMF/UPF dan NWDAF dapat dirangkai secara konseptual menjadi loop intent–enforcement–compliance dengan bounded policy adaptation. Admission limit menjadi actuator utama; stabilitas dibahas secara analitis. | D45: Target usulan: p99 delay ≤50 ms, loss ≤10⁻³ (0,1%), warning 50–55 ms, window W=2 s, dan persistence 3 window. Ini target/parameter, bukan hasil eksperimen. Batas kontrol Rctrl≤NB/Ts dan stabilitas lokal 0<K<2/G bergantung asumsi model. | E45: Belum ada bukti empiris manfaat/recovery; UPF measurements memerlukan konteks radio untuk interpretasi E2E. Pemilihan p99 50 ms adalah desain penulis, bukan persyaratan p99 universal 3GPP. | F45: Usulan: gunakan sebagai acuan feedback, bounded actuation, dan baseline desain core-only; validasi koordinasi RIC–NWDAF, lokasi bottleneck, dan pemulihan SLA per slice melalui eksperimen yang dapat direproduksi. | G45: =INDEX(PAPER!$B$2:$B$45,MATCH(A45,PAPER!$A$2:$A$45,0)) -> Closed-Loop L4S-as-a-Service in 5G-Advanced: NEF–PCF Control with NWDAF-Driven Assurance
A49: No Paper Pendukung | B49: Aspek / Arah Riset | C49: Kondisi Terkini dalam Corpus | D49: Rancangan Benchmark Lanjutan | E49: Celah Gabungan dalam Corpus | F49: Posisi Penelitian Anda (Usulan)
A50: 2, 6, 16, 20, 30, 31, 32, 33, 38, 39, 40, 41, 42, 43, 44 | B50: Prioritas utama: bottleneck-aware RAN–core steering | C50: Bottleneck-aware rApp–xApp resource control (39), tracing/diagnosis RAN–core (40), observability core (41), hybrid RAN steering (42), prediksi QoS per slice (43), dan NWDAF assurance analitis (44) sudah tersedia. Integrasi komponen dan diagnosis saja tidak cukup untuk novelty. | D50: Baseline: RAN-only, core/path-only, controller terpisah, koordinator tanpa diagnosis, dan oracle lokasi bottleneck. Skenario: RAN-only, core-only, gabungan, dan bottleneck berpindah; workload dan budget disamakan. | E50: Dalam corpus terakses, belum ada satu evaluasi terpadu diagnosis–pemilihan aksi RAN/core/gabungan–pemulihan SLA multi-slice melalui RIC–NWDAF. Diagnosis lintas domain sudah dibahas; no 44 belum memiliki hasil eksperimen. | F50: Hipotesis kontribusi: pemilihan domain steering berbasis lokasi bottleneck menurunkan SLA violation, recovery time, dan aksi sia-sia. Uji manfaat diagnosis melalui ablation; belum merupakan klaim pertama secara global.
A51: 30, 31, 32, 33, 34, 39, 42, 44 | B51: Koordinator rApp dan pemisahan analytics/actuation | C51: rApp/xApp dapat menegakkan kebijakan bottleneck-aware (39); NWDAF menyediakan compliance analytics dan PCF/SMF/UPF merealisasikan aksi core (32, 44). No 44 adalah desain analitis, bukan integrasi RIC yang telah diuji. | D51: Mulai satu aksi RAN yang didukung testbed dan satu aksi core/path. Catat observasi, keputusan, ACK, efek QoS, timeout, dan rollback. Uji delay/reordering telemetry, policy mismatch, dan actuation gagal. | E51: Endpoint RIC–NWDAF dan core adapter harus eksplisit; NWDAF bukan pengubah forwarding. Task migration (39), handover (42), dan admission/PCC update (44) merupakan aksi berbeda sehingga tidak dapat disamakan. | F51: Rancang arbitration lintas timescale dan domain, bounded update, serta verifikasi efek aksi. Jelaskan API yang diimplementasikan; hysteresis/rollback adalah mekanisme pendukung yang manfaatnya diuji melalui ablation.
A52: 31, 35, 36, 40, 41, 43, 44 | B52: Observability untuk diagnosis bottleneck | C52: User-plane telemetry (36), signaling tracing RAN–core (40), core temporal knowledge graph (41), dan QoS predictor radio (43) memberi jenis visibility berbeda. No 44 memformalkan compliance feedback. | D52: Bandingkan KPI rata-rata versus tail/distribution; fresh versus delayed/missing telemetry; fitur dengan/tanpa dependency/tracing. Ground truth lokasi berasal dari injeksi bottleneck terkendali. | E52: Anomaly F1, Precision@K, trace accuracy, BLER prediction, dan compliance threshold bukan metrik yang identik. Akurasi pada skenario injeksi tidak otomatis menjadi akurasi multiclass lokasi RAN/core. | F52: Uji precision/recall atau Macro-F1 lokasi bottleneck dan pemilihan aksi, lalu hubungkan budget/freshness telemetry dengan recovery time dan SLA per slice. Pisahkan diagnosis signaling dan bottleneck user-plane.
A53: 8, 14, 18, 20, 30, 34, 37, 38, 39, 42, 43, 44 | B53: Validasi multi-slice dan efek samping | C53: QoS slicing, radio steering, isolation, dan load stability telah diukur pada konteks masing-masing. No 43 menekankan label per-slice; no 44 menyediakan target dan blueprint, bukan pencapaian empiris. | D53: Gunakan topology, traffic, target SLA, dan resource budget yang sama. Laporkan seed/repetisi dan interval kepercayaan, p95/p99 delay, throughput/loss, SLA violation per slice, recovery time, fairness, churn, dan overhead. | E53: Task delay (39), per-BS Jain fairness/preference (42), BLER violation (43), dan target p99 delay (44) tidak dapat digabung menjadi satu benchmark SLA E2E. Perbaikan satu slice dapat menggeser bottleneck ke slice lain. | F53: Kontribusi eksperimen: pemulihan SLA per slice saat bottleneck berpindah, beserta cross-slice impact, stability, rejection/admission cost, dan overhead. Batas SLA ditetapkan sesuai layanan, bukan menyalin angka paper secara langsung.
A54: 7, 18, 20, 15, 8 | B54: Alternatif corpus awal: Prioritas awal: safe SLA-adaptive slicing | C54: Contract intent (CAIF), PPO SLA-aware, online QoS slicing (xSlice) dan substrate ORANSlice sudah tersedia secara terpisah. | D54: Bandingkan rule-based, PPO/xSlice tanpa shield, dan controller dengan shield; gunakan skenario demand/SLA berubah serta resource tidak cukup. | E54: Corpus belum menunjukkan satu evaluasi yang mengisolasi manfaat contract + per-action constraint di bawah stale telemetry dan SLA berubah. | F54: Usulan: validator state-aware dan feasible action projection antara intent/policy dan xApp. Target kontribusi: menekan violation/unsafe action dengan biaya latency dan false rejection yang terukur.
A55: 6, 16, 10, 17, 28 | B55: Alternatif corpus awal: Delay-aware coordination lintas-timescale | C55: rApp/xApp serta rApp/xApp/dApp sudah diusulkan; beberapa hasil memakai kondisi komunikasi ideal atau simulasi. | D55: Ablation: tanpa koordinasi, koordinasi ideal, koordinasi delay-aware. Ukur fairness, policy churn, SLA dan robustness terhadap delay/loss. | E55: Koordinasi ideal belum membuktikan stabilitas saat policy tiba terlambat, version mismatch atau state berbeda antar-loop. | F55: Usulan: policy versioning, validity interval, hysteresis dan scheduling update. Tahap awal dua loop; perluasan dApp setelah manfaat dua loop terbukti.
A56: 2, 12, 1, 27, 39, 40, 44 | B56: Alternatif corpus awal: Joint RAN–core SLA assurance | C56: NWDAF core automation, O-RAN bottleneck control, tracing RAN–core, dan desain latency assurance sudah memiliki fondasi; tujuan, actuator, serta bukti evaluasinya berbeda. | D56: Baseline RAN-only, core-only, independent dual controller, dan joint bottleneck-aware controller pada congestion radio/core. Tambahkan ablation tanpa diagnosis dan oracle lokasi bottleneck. | E56: Diagnosis atau koordinasi arsitektur saja belum membuktikan bahwa aksi yang dipilih memulihkan SLA trafik. No 40 berfokus signaling dan no 44 belum divalidasi secara empiris. | F56: Usulan: controller joint bottleneck-aware berbasis telemetry dua domain dengan API actuation eksplisit. Uji causal chain observasi–diagnosis–aksi–efek QoS serta batas overhead dan stabilitas.
A57: 7, 26, 11, 15 | B57: Alternatif corpus awal: Verifiable agentic control | C57: LLM/SLM hierarchy dan intent contract telah muncul; attack surface xApp/ML juga dipetakan. | D57: Baseline direct-actuation, schema-only, contract statis, contract state-aware; samakan model/parameter untuk ablation. | E57: Akurasi intent dataset kurasi belum menjamin keamanan pada adversarial intent, conflicting goals dan drift operational state. | F57: Usulan: runtime contract monitoring dan rollback/fallback. Uji semantic errors, unsafe execution, rejection salah, recovery dan biaya inferensi.
A58: 23, 24, 4, 29 | B58: Alternatif corpus awal: Deadline-aware placement dan dApp actuation | C58: Characterization container/SmartNIC, placement RIC-O dan E3 telemetry OCUDU telah memberi fondasi resource/timing. | D58: Static placement vs workload-aware placement; ukur total loop serta downtime migration, bukan inference/telemetry saja. | E58: Benchmark memakai budget/hardware berbeda: sub-ms dApp, 10 ms workload dan waktu recovery detik tidak dapat digabung sebagai satu angka. | F58: Usulan: profiler + admission/placement sesuai latency-tail; kompleksitas tinggi bila membutuhkan accelerator/RU. Gunakan replay workload untuk eksperimen tahap awal.
